cchttpserver
