Metadata-Version: 1.1
Name: cchttpserver
Version: 0.6.3
Summary: http server for claimchain blocks
Home-page: https://cchttpserver.readthedocs.io
Author: UNKNOWN
Author-email: UNKNOWN
License: MIT license
Platform: unix
Platform: linux
Platform: osx
Platform: cygwin
Platform: win32
Classifier: Development Status :: 3 - Alpha
Classifier: Intended Audience :: Developers
Classifier: License :: OSI Approved :: MIT License
Classifier: Operating System :: POSIX
Classifier: Operating System :: MacOS :: MacOS X
Classifier: Topic :: Utilities
Classifier: Intended Audience :: Developers
Classifier: Programming Language :: Python
